{"title":"BBC News 코리아 ─ 다운로드","url":"https://www.bbc.com/korean/downloads","favicon":"https://www.bbc.com/korean/favicon.ico","elements":[{"title":"2024년 4월 1일","contents":"korean-2024-04-01-HQ.zip, <span>14 MB</span>","link":"https://ws-downloads.files.bbci.co.uk/korean-2024-04-01-HQ.zip","retrieved":1711998620450},{"title":"2024년 3월 29일","contents":"korean-2024-03-29-HQ.zip, <span>14 MB</span>","link":"https://ws-downloads.files.bbci.co.uk/korean-2024-03-29-HQ.zip","retrieved":1711736209587},{"title":"2024년 3월 28일","contents":"korean-2024-03-28-HQ.zip, <span>14 MB</span>","link":"https://ws-downloads.files.bbci.co.uk/korean-2024-03-28-HQ.zip","retrieved":1711652993685},{"title":"2024년 3월 27일","contents":"korean-2024-03-27-HQ.zip, <span>14 MB</span>","link":"https://ws-downloads.files.bbci.co.uk/korean-2024-03-27-HQ.zip","retrieved":1711566691826},{"title":"2024년 3월 26일","contents":"korean-2024-03-26-HQ.zip, <span>14 MB</span>","link":"https://ws-downloads.files.bbci.co.uk/korean-2024-03-26-HQ.zip","retrieved":1711484044123},{"title":"2024년 3월 25일","contents":"korean-2024-03-25-HQ.zip, <span>14 MB</span>","link":"https://ws-downloads.files.bbci.co.uk/korean-2024-03-25-HQ.zip","retrieved":1711390635534},{"title":"2024년 3월 22일","contents":"korean-2024-03-22-HQ.zip, <span>14 MB</span>","link":"https://ws-downloads.files.bbci.co.uk/korean-2024-03-22-HQ.zip","retrieved":1711131408199},{"title":"2024년 3월 21일","contents":"korean-2024-03-21-HQ.zip, <span>14 MB</span>","link":"https://ws-downloads.files.bbci.co.uk/korean-2024-03-21-HQ.zip","retrieved":1711052043615},{"title":"2024년 3월 20일","contents":"korean-2024-03-20-HQ.zip, <span>14 MB</span>","link":"https://ws-downloads.files.bbci.co.uk/korean-2024-03-20-HQ.zip","retrieved":1710965670929},{"title":"2024년 3월 19일","contents":"korean-2024-03-19-HQ.zip, <span>14 MB</span>","link":"https://ws-downloads.files.bbci.co.uk/korean-2024-03-19-HQ.zip","retrieved":1710875512616},{"title":"2024년 3월 18일","contents":"korean-2024-03-18-HQ.zip, <span>14 MB</span>","link":"https://ws-downloads.files.bbci.co.uk/korean-2024-03-18-HQ.zip","retrieved":1710785793431},{"title":"2024년 3월 15일","contents":"korean-2024-03-15-HQ.zip, <span>14 MB</span>","link":"https://ws-downloads.files.bbci.co.uk/korean-2024-03-15-HQ.zip","retrieved":1710526660161},{"title":"2024년 3월 14일","contents":"korean-2024-03-14-HQ.zip, <span>14 MB</span>","link":"https://ws-downloads.files.bbci.co.uk/korean-2024-03-14-HQ.zip","retrieved":1710443438237},{"title":"2024년 3월 13일","contents":"korean-2024-03-13-HQ.zip, <span>14 MB</span>","link":"https://ws-downloads.files.bbci.co.uk/korean-2024-03-13-HQ.zip","retrieved":1710353784778}]}