{"title":"BBC News 코리아 ─ 다운로드","url":"https://www.bbc.com/korean/downloads","favicon":"https://www.bbc.com/korean/favicon.ico","elements":[{"title":"2022년 5월 2일","contents":"korean-2022-05-02-HQ.zip, <span>28 MB</span>","link":"https://ws-downloads.files.bbci.co.uk/korean-2022-05-02-HQ.zip","retrieved":1651518868857},{"title":"2022년 5월 1일","contents":"korean-2022-05-01-HQ.zip, <span>28 MB</span>","link":"https://ws-downloads.files.bbci.co.uk/korean-2022-05-01-HQ.zip","retrieved":1651432445253},{"title":"2022년 4월 30일","contents":"korean-2022-04-30-HQ.zip, <span>28 MB</span>","link":"https://ws-downloads.files.bbci.co.uk/korean-2022-04-30-HQ.zip","retrieved":1651349843412},{"title":"2022년 4월 29일","contents":"korean-2022-04-29-HQ.zip, <span>28 MB</span>","link":"https://ws-downloads.files.bbci.co.uk/korean-2022-04-29-HQ.zip","retrieved":1651259631349},{"title":"2022년 4월 28일","contents":"korean-2022-04-28-HQ.zip, <span>28 MB</span>","link":"https://ws-downloads.files.bbci.co.uk/korean-2022-04-28-HQ.zip","retrieved":1651173265869},{"title":"2022년 4월 27일","contents":"korean-2022-04-27-HQ.zip, <span>28 MB</span>","link":"https://ws-downloads.files.bbci.co.uk/korean-2022-04-27-HQ.zip","retrieved":1651086828063},{"title":"2022년 4월 26일","contents":"korean-2022-04-26-HQ.zip, <span>28 MB</span>","link":"https://ws-downloads.files.bbci.co.uk/korean-2022-04-26-HQ.zip","retrieved":1651000412034},{"title":"2022년 4월 25일","contents":"korean-2022-04-25-HQ.zip, <span>28 MB</span>","link":"https://ws-downloads.files.bbci.co.uk/korean-2022-04-25-HQ.zip","retrieved":1650914013822},{"title":"2022년 4월 24일","contents":"korean-2022-04-24-HQ.zip, <span>28 MB</span>","link":"https://ws-downloads.files.bbci.co.uk/korean-2022-04-24-HQ.zip","retrieved":1650827619031},{"title":"2022년 4월 23일","contents":"korean-2022-04-23-HQ.zip, <span>28 MB</span>","link":"https://ws-downloads.files.bbci.co.uk/korean-2022-04-23-HQ.zip","retrieved":1650741236242},{"title":"2022년 4월 22일","contents":"korean-2022-04-22-HQ.zip, <span>28 MB</span>","link":"https://ws-downloads.files.bbci.co.uk/korean-2022-04-22-HQ.zip","retrieved":1650658677892},{"title":"2022년 4월 21일","contents":"korean-2022-04-21-HQ.zip, <span>28 MB</span>","link":"https://ws-downloads.files.bbci.co.uk/korean-2022-04-21-HQ.zip","retrieved":1650568363718},{"title":"2022년 4월 20일","contents":"korean-2022-04-20-HQ.zip, <span>28 MB</span>","link":"https://ws-downloads.files.bbci.co.uk/korean-2022-04-20-HQ.zip","retrieved":1650482047348},{"title":"2022년 4월 19일","contents":"korean-2022-04-19-HQ.zip, <span>28 MB</span>","link":"https://ws-downloads.files.bbci.co.uk/korean-2022-04-19-HQ.zip","retrieved":1650395894124}]}