{"title":"BBC News 코리아 ─ TOP 뉴스","url":"https://www.bbc.com/korean/popular/read","favicon":"https://static.files.bbci.co.uk/ws/simorgh-assets/public/korean/images/icons/icon-72x72.png","elements":[{"title":"BTS부터 레이디 가가까지...사진으로 보는 그래미 레드카펫","contents":"1","link":"https://www.bbc.com/korean/60951176","retrieved":1649049322342},{"title":"우크라이나 수도 탈환...러시아 '민간인 학살' 의혹 확인","contents":"2","link":"https://www.bbc.com/korean/international-60975390","retrieved":1649041357901},{"title":"코로나19 확진자는 언제까지 전염력이 있나?","contents":"3","link":"https://www.bbc.com/korean/features-60034967","retrieved":1647966563314},{"title":"우크라이나 전쟁: 불에 탄 시신과 탱크로 뒤덮인 부차의 거리","contents":"4","link":"https://www.bbc.com/korean/international-60978512","retrieved":1649046001278},{"title":"방탄소년단 '넘지 못한 그래미 벽'","contents":"5","link":"https://www.bbc.com/korean/news-60950197","retrieved":1649053245604},{"title":"한국, 코로나19 '엔데믹' 첫 국가되나?","contents":"6","link":"https://www.bbc.com/korean/news-60950196","retrieved":1648794049136},{"title":"러시아가 우크라이나를 침공한 이유","contents":"7","link":"https://www.bbc.com/korean/60521326","retrieved":1648937736607},{"title":"러시아 최정예 낙하산 부대 '막대한 전력손실'...최소 39명 사망 확인","contents":"8","link":"https://www.bbc.com/korean/news-60978513","retrieved":1649053245607},{"title":"가슴 통증에 만성 피로감, 혹시 나도?...'롱코비드' 후유증은 무엇인가","contents":"9","link":"https://www.bbc.com/korean/60936699","retrieved":1648804527420},{"title":"'스텔스 오미크론' BA.2는 무엇인가","contents":"10","link":"https://www.bbc.com/korean/60900150","retrieved":1648628437602}]}