{"title":"BBC News 코리아 ─ BBC 코리아 라디오","url":"https://www.bbc.com/korean","favicon":"https://static.files.bbci.co.uk/ws/simorgh-assets/public/korean/images/icons/icon-72x72.png","elements":[{"title":"2022년 3월 5일","contents":"<span class=\"bbc-1gnhmg2 e1yt7oin0\">듣기, </span>English Learning with BBC<span class=\"bbc-1gnhmg2 e1yt7oin0\">, 00:49, </span><span class=\"bbc-1k5mnnp evmopx62\">2022년 3월 5일</span><span class=\"bbc-1gnhmg2 e1yt7oin0\">, 방송 길이 11,00 </span>","link":"https://www.bbc.com/korean/bbc_korean_radio/w3ct2ldb","retrieved":1646410945161},{"title":"2022년 3월 5일","contents":"<span class=\"bbc-1gnhmg2 e1yt7oin0\">듣기, </span>BBC 코리아 라디오<span class=\"bbc-1gnhmg2 e1yt7oin0\">, 00:30, </span><span class=\"bbc-1k5mnnp evmopx62\">2022년 3월 5일</span><span class=\"bbc-1gnhmg2 e1yt7oin0\">, 방송 길이 19,00 </span>","link":"https://www.bbc.com/korean/bbc_korean_radio/w3ct2lkz","retrieved":1646410945162},{"title":"2022년 3월 4일","contents":"<span class=\"bbc-1gnhmg2 e1yt7oin0\">듣기, </span>English Learning with BBC<span class=\"bbc-1gnhmg2 e1yt7oin0\">, 00:49, </span><span class=\"bbc-1k5mnnp evmopx62\">2022년 3월 4일</span><span class=\"bbc-1gnhmg2 e1yt7oin0\">, 방송 길이 11,00 </span>","link":"https://www.bbc.com/korean/bbc_korean_radio/w3ct2lgl","retrieved":1646324587719}]}